sage_acsv/__init__.py
sage_acsv/asymptotics.py
sage_acsv/debug.py
sage_acsv/groebner.py
sage_acsv/helpers.py
sage_acsv/kronecker.py
sage_acsv/settings.py
sage_acsv/whitney.py
sage_acsv/backends/__init__.py
sage_acsv/backends/default.py
sage_acsv/backends/macaulay2.py
sage_acsv/backends/msolve.py
sage_acsv-0.3.0.dist-info/METADATA
sage_acsv-0.3.0.dist-info/WHEEL
sage_acsv-0.3.0.dist-info/licenses/LICENSE
sage_acsv-0.3.0.dist-info/RECORD
