Metadata-Version: 2.4
Name: sage-acsv
Version: 0.3.0
Summary: A SageMath package with algorithms for analytic combinatorics in several variables.
Project-URL: repository, https://github.com/ACSVMath/sage_acsv
Author-email: Benjamin Hackl <devel@benjamin-hackl.at>, Andrew Luo <j92luo@uwaterloo.ca>, Stephen Melczer <steve.melczer@uwaterloo.ca>, Jesse Selover <jselover@umass.edu>, Elaine Wong <elaine.wong@ricam.oeaw.ac.at>
License: MIT License
License-File: LICENSE
Requires-Python: >=3.9
